coffee_grinds/__init__.py
coffee_grinds/__main__.py
coffee_grinds/config/__init__.py
coffee_grinds/config/definitions.py
coffee_grinds/utils.py
coffee_grinds-0.0.1.dist-info/LICENSE
coffee_grinds-0.0.1.dist-info/METADATA
coffee_grinds-0.0.1.dist-info/WHEEL
coffee_grinds-0.0.1.dist-info/RECORD
