Metadata-Version: 2.3
Name: coffee-grinds
Version: 0.0.1
Summary: Code to run a coffee grinder with a QT Py ESP32
Author: Tsmorz
Author-email: tonysmoragiewicz@gmail.com
Requires-Python: >=3.11,<3.13
Classifier: Programming Language :: Python :: 3
Classifier: Programming Language :: Python :: 3.11
Classifier: Programming Language :: Python :: 3.12
Requires-Dist: loguru (>=0.7.3,<0.8.0)
Requires-Dist: numpy (>=2.2.3,<3.0.0)
Project-URL: homepage, https://github.com/Tsmorz/coffee-grinder
